{"kanji":"芝","hanzi-su-wiki":"<h1>芝</h1> <h2>Значения</h2><p>Дёрн, газон</p><h2>Мнемоника</h2><p>Молодые ростки <a href=\"http://hanzi.su/wiki/之\">之</a> и сухая трава <a href=\"http://hanzi.su/wiki/艹\">艹</a> образуют дёрн.</p>","purpleculture_pinyin":"<div class=\"my-pinyin-image-container pinyin-zhi pinyin-number-1\"><span></span><img><img></div>   <div class=\"my-pinyin-tone\"><a class=\"pinyin tone1 \" href=\"https://www.purpleculture.net/mp3/zhi1.mp3\">zhī</a></div>   <div class=\"my-pinyin-english\">Zoysia pungens</div>   <div class=\"my-pinyin-ru\">Зойсия пунгенс</div>","chinese_junda_freq_ierogliph_number":"2150","heisig_id":"1301","rtega_mnemonic":"<table><tr><td>芝芝<a href=\"http://rtega.be/chmn/?reversec=芝\">R</a><a href=\"http://rtega.be/chmn/index.php?submit=2781\">S</a></td><td></td><td>turf, lawn, purplish fungus symbolizing nobility, kind of fragrant herb</td><td><ul><li title=\"Reinaert Albrecht\">grass <a href=\"http://rtega.be/chmn/?c=艹\">艹</a> shooting out of the ground <a href=\"http://rtega.be/chmn/?c=之\">之</a></li></ul></td><td></td></tr></table>","purpleculture_info":"<div><div ><div ></div> <div><b>Pictophonetic</b>: <span class=\"semantic\"><a class=\"dictips\">之</a></span> indicates the sound; <span class=\"phonetic\"><a class=\"dictips\">艹</a></span> (plant) conveys the meaning.</div></div></div>","purpleculture_examples":"<a class=\"sword\" href=\"https://www.purpleculture.net/dictionary-details?word=%E8%8A%9D%E9%BA%BB\">芝麻</a> [ <a class=\"pinyin tone1 \" href=\"https://www.purpleculture.net/mp3/zhi1.mp3\">zhī</a> <a class=\"pinyin tone5 \" href=\"https://www.purpleculture.net/mp3/ma5.mp3\">ma</a> ]: sesame (seed)<br><a class=\"sword\" href=\"https://www.purpleculture.net/dictionary-details?word=%E7%81%B5%E8%8A%9D\">灵芝</a> [ <a class=\"pinyin tone2 \" href=\"https://www.purpleculture.net/mp3/ling2.mp3\">líng</a> <a class=\"pinyin tone1 \" href=\"https://www.purpleculture.net/mp3/zhi1.mp3\">zhī</a> ]: lingzhi or reishi mushroom (Ganoderma lucidum)<br><a class=\"sword\" href=\"https://www.purpleculture.net/dictionary-details?word=%E8%8A%9D%E9%BA%BB%E5%AE%98\">芝麻官</a> [ <a class=\"pinyin tone1 \" href=\"https://www.purpleculture.net/mp3/zhi1.mp3\">zhī</a> <a class=\"pinyin tone5 \" href=\"https://www.purpleculture.net/mp3/ma5.mp3\">ma</a> <a class=\"pinyin tone1 \" href=\"https://www.purpleculture.net/mp3/guan1.mp3\">guān</a> ]: low ranking official; petty bureaucrat<br><a class=\"sword\" href=\"https://www.purpleculture.net/dictionary-details?word=%E8%8A%9D%E9%BA%BB%E9%85%B1\">芝麻酱</a> [ <a class=\"pinyin tone1 \" href=\"https://www.purpleculture.net/mp3/zhi1.mp3\">zhī</a> <a class=\"pinyin tone5 \" href=\"https://www.purpleculture.net/mp3/ma5.mp3\">ma</a> <a class=\"pinyin tone4 \" href=\"https://www.purpleculture.net/mp3/jiang4.mp3\">jiàng</a> ]: sesame paste<br><a class=\"sword\" href=\"https://www.purpleculture.net/dictionary-details?word=%E8%8A%9D%E9%BA%BB%E6%B2%B9\">芝麻油</a> [ <a class=\"pinyin tone1 \" href=\"https://www.purpleculture.net/mp3/zhi1.mp3\">zhī</a> <a class=\"pinyin tone5 \" href=\"https://www.purpleculture.net/mp3/ma5.mp3\">ma</a> <a class=\"pinyin tone2 \" href=\"https://www.purpleculture.net/mp3/you2.mp3\">yóu</a> ]: sesame oil","purpleculture_tree":"<div class=\"tree\"><ul><li><span class=\"str_def\">⿱</span> <span class=\"str_desc\">Above to below</span><ul><li><span class=\"str_def\"><a class=\"dictips\">艹</a></span> <span class=\"str_py\">[ <a class=\"pinyin tone3 \" href=\"https://www.purpleculture.net/mp3/cao3.mp3\">cǎo</a> ]</span> <span class=\"str_desc\">grass, weed, plant, herb</span></li><li><span class=\"str_def\"><a class=\"dictips\">之</a></span> <span class=\"str_py\">[ <a class=\"pinyin tone1 \" href=\"https://www.purpleculture.net/mp3/zhi1.mp3\">zhī</a> ]</span> <span class=\"str_desc\">marks preceding phrase as modifier of following phrase; it, him her, them; to go to</span></li></ul></li></ul></div>","purpleculture_img":"https://www.purpleculture.net/images/stroke/37721309.jpg","heisig_keyword":"turf | дерн","heisig_chinese_memo":"Zorro, with a flower between his teeth for the ladies, defends his turf where he harvests black sesame. \"This is my turf! And this...is for the lady, as he hands her some Chinese black sesame pudding.\".","heisig_frameNoV4":"1216","heisig_frameNoV6":"1301","heisig_constituent":"turf, flowers, of, Zorro, building blocks, zig-zag","heisig_story":"Flowers . . . building blocks.","heisig_lessonNo":"32","Keyword_KKLC":"LAWN GRASS","Keyword_KKLC_ru":"газонные травы","Keyword_KANJIDIC":"turf, lawn","Keyword_KANJIDIC_ru":"дерн, лужайка","strokeDiagram":"<img src=\"E88A9D.png\" />","strokeCount":"6","koohiiStory1":"Artificial turf made easy: flowers stuck on top of building blocks that you can place anywhere.","koohiiStory2":"Zorro, with a flower between his teeth for the ladies, defends his turf against evildoers. \"This is my turf! And this...is for the lady.\".","jouYou":"JH","jlpt":"1","onYomi":"シ","kunYomi":"しば","jp_example_words":"芝(しば): lawn, sod, turf<br>芝居(しばい): play, drama<br>芝生(しばふ): lawn","jp_readingExamples":"芝 (しば)","jp_sound":"[sound:oddcast-4a26c636-a813545b-002de179-3ae28751-46e9a6c6.mp3]","WaniKani_Kanji_Meaning":"Lawn","WaniKani_Radicals":"艹","WaniKani_Radical_Icons":"<i class=\"radical-hills\"></i>","WaniKani_Radical_Names":"flowers","WaniKani_Radical_Icons_Names":"hills","WaniKani_Meaning_Mnemonic":"There are <span class=\"radical-highlight\" title=\"Radical\" rel=\"tooltip\">flowers</span> and <span class=\"radical-highlight\" title=\"Radical\" rel=\"tooltip\">hills</span> in your front <span class=\"kanji-highlight\" title=\"Kanji\" rel=\"tooltip\">lawn</span>. Your lawn is pretty big and it is covered with both flowers and hills. It’s very pretty.","WaniKani_Meaning_Info":"Imagine walking through your lawn and smelling all the flowers as you travel over the rolling hills. What a delightful lawn this is.","WaniKani_Reading_Mnemonic":"You are the proud owner of a <span class=\"reading-highlight\" title=\"Reading\" rel=\"tooltip\">Shiba</span> (<span lang=\"ja\">しば</span>) Inu, y’know, the Japanese dog? Well, this Shiba Inu of yours loves to run around in your <span class=\"kanji-highlight\" title=\"Kanji\" rel=\"tooltip\">lawn</span> and through the flowers and over the hills. This is the perfect lawn for your Shiba.","WaniKani_Reading_Info":"Look at your little Shiba running through the lawn all happy and elated. Hear him barking as he zooms up and down each hill.","Ru_Russian":"трава, дёрн, газон","Ru_YarxiRusNick":"газон","Ru_Meaning":"turf, lawn","Ru_Notes":"Также: 芝居 (しばい театральная постановка);","Ru_Radicals":"亠 (крышка), 艾 (мокса)","Ru_trainchinese":"<span class=\"trainchinese-pinyin\">zhī</span>: (<span class=\"trainchinese-type\">графема</span>) <span class=\"trainchinese-transl\">ароматная трава, пурпурный гриб, символизирующий благородство</span>","Kanshudo_mnemonic":"of (<a href='/kanji/%E4%B9%8B'>之</a>) grass (<a href='/kanji/%E8%89%B9'>艹</a>) = a lawn","chinese_mnemonics_deck__meaning":"sesame","chinese_mnemonics_deck__story":"Zorro, with a flower between his teeth for the ladies, defends his turf where he harvests black sesame. \"This is my turf! And this...is for the lady, as he hands her some Chinese black sesame pudding.\".","chinese_mnemonics_deck__diagram":"<img src='lf_33437.gif'/>","chinese_mnemonics_deck__kind":"both","humanum_full_description_en":"From &quot;<a href=\"http://humanum.arts.cuhk.edu.hk/Lexis/lexi-mf/search.php?word==%E8%89%B8\">艸</a>&quot;, &quot; <a href=\"http://humanum.arts.cuhk.edu.hk/Lexis/lexi-mf/search.php?word==%E4%B9%8B\">Zhi</a> &quot; sound. The original meaning is Ganoderma lucidum, a fungus plant. The ancients thought it was Seocho. &quot;Said Wen&quot;: &quot;Zhi, the gods are also. From the chasing to it.&quot; &quot;Jade chapter. Caobu&quot;: &quot;Zhi, Seocho.&quot; Such as &quot;Historical Records. &quot;Xiaowu Benji&quot;: &quot;The nine stems of Ganquan Fangshengzhi, forgiving the world, there is no duplication.&quot; &quot;Lun Heng. Verification of Symbols: &quot;Zhi grass extends the year, eaten by immortals.&quot;<br><br> &quot; <a href=\"http://humanum.arts.cuhk.edu.hk/Lexis/lexi-mf/search.php?word==%E8%8A%9D\">Zhi</a> &quot; also means Baizhi, which is a kind of vanilla. Such as &quot;Selected Works. Lu Shiheng&#39;s &quot;Sigh for the Death&quot;: &quot;Believe in the pine and luxuriant but Park Hyatt, sigh the zhi burn and sigh.&quot; Li Zhouhan&#39;s note: &quot;Zhi, vanilla.&quot; In ancient books, &quot;Zhi Lan&quot; is often used together, such as &quot;Confucius&#39; Family Language. &quot;Zai E&quot;: &quot;Also, Zhilan was born in the deep forest, and he does not think that there is no one but is not fragrant; a gentleman cultivates virtue and does not lose his life for poverty.&quot;","humanum_short_description_en":"From &quot;<a href=\"http://humanum.arts.cuhk.edu.hk/Lexis/lexi-mf/search.php?word==%E8%89%B8\">艸</a>&quot;, &quot; <a href=\"http://humanum.arts.cuhk.edu.hk/Lexis/lexi-mf/search.php?word==%E4%B9%8B\">Zhi</a> &quot; sound. The original meaning is Ganoderma lucidum, a fungus plant.","humanum_full_description":"從「<a href=\"http://humanum.arts.cuhk.edu.hk/Lexis/lexi-mf/search.php?word==%E8%89%B8\">艸</a>」，「<a href=\"http://humanum.arts.cuhk.edu.hk/Lexis/lexi-mf/search.php?word==%E4%B9%8B\">之</a>」聲。本義是靈芝草，一種菌類植物。古人認為是瑞草。《說文》：「芝，神艸也。从艸从之。」《玉篇．草部》：「芝，瑞草。」如《史記．孝武本紀》：「甘泉防生芝九莖，赦天下，毋有復作。」《論衡．驗符》：「芝草延年，仙者所食。」<br> <br> 　　「<a href=\"http://humanum.arts.cuhk.edu.hk/Lexis/lexi-mf/search.php?word==%E8%8A%9D\">芝</a>」又表示白芷，是一種香草。如《文選．陸士衡〈歎逝賦〉》：「信松茂而柏悅，嗟芝焚而蕙歎。」李周翰注：「芝，香草也。」古書裡常以「芝蘭」連用，如《孔子家語．在厄》：「且芝蘭生於深林，不以無人而不芳；君子修道立德，不為窮困而敗節。」","humanum_short_description":"從「<a href=\"http://humanum.arts.cuhk.edu.hk/Lexis/lexi-mf/search.php?word==%E8%89%B8\">艸</a>」，「<a href=\"http://humanum.arts.cuhk.edu.hk/Lexis/lexi-mf/search.php?word==%E4%B9%8B\">之</a>」聲。本義是靈芝草，一種菌類植物。","humanum_img_url":"http://humanum.arts.cuhk.edu.hk/Lexis/lexi-mf/kangxiArchaic.php?hash=ba5cf909d016d95c506b88a5335ad8bf","_purpleculture_dictionary_orig_full":"<div class=\"d-flex\"><div style=\"line-height:1.6\"><div id=\"sen0\"><ruby class=\"mainsc\">芝</ruby><div class=\"btn-group px-2\"><a class=\"btn btn-default px-1 text-muted\" href=\"/mp3/zhi1.mp3\"> <i class=\"fas fa-volume-up\" aria-hidden=\"true\" data-toggle=\"tooltip\" title=\"Speak\"></i></a> </div></div><b>Pinyin: </b> <a class=\"pinyin tone1 \" href=\"/mp3/zhi1.mp3\">zhī</a><br><b>English Definition: </b><span class=\"en\">Zoysia pungens</span><br><div class=\"clearBoth\"></div><div class=\"charstr\"><b>Total strokes:</b> 7; <b>Radical:</b> <a href=\"javascript:;\" class=\"radicaltips tips\" title=\"艸 (艹) [ <a class='pinyin tone3 ' href='/mp3/cao3.mp3'>cǎo</a>] <a href='radical/?id=140' class='ml-2'> <i class='fas fa-external-link-alt text-muted'></i></a> <br><br>grass\">艸</a></div><div><b>Pictophonetic</b>: <span class=\"semantic\"><a href=\"javascript:\" class=\"dictips\" title=\"loading...\">之</a></span> indicates the sound; <span class=\"phonetic\"><a href=\"javascript:\" class=\"dictips\" title=\"loading...\">艹</a></span> (plant) conveys the meaning.</div><div><b>Character Formation:</b></div><div class=\"tree\"><ul><li><span class=\"str_def\">⿱</span> <span class=\"str_desc\">Above to below</span><ul><li><span class=\"str_def\"><a href=\"javascript:\" class=\"dictips\" title=\"loading...\">艹</a></span> <span class=\"str_py\">[ <a class=\"pinyin tone3 \" href=\"/mp3/cao3.mp3\">cǎo</a> ]</span> <span class=\"str_desc\">grass, weed, plant, herb</span></li><li><span class=\"str_def\"><a href=\"javascript:\" class=\"dictips\" title=\"loading...\">之</a></span> <span class=\"str_py\">[ <a class=\"pinyin tone1 \" href=\"/mp3/zhi1.mp3\">zhī</a> ]</span> <span class=\"str_desc\">marks preceding phrase as modifier of following phrase; it, him her, them; to go to</span></li></ul></li></ul></div><div class=\"py-2\"><b>Step by Step Stroke Sequence:</b><span id=\"stroke_tool\"><a class=\"btn btn-sm btn-link text-muted\" href=\"/images/stroke/37721309.jpg\" download=\"stroke_sequence.jpg\" data-toggle=\"tooltip\" title=\"Download the chart\"><i class=\"fa fa-download\" aria-hidden=\"true\"></i> Download</a> <a class=\"btn btn-sm btn-link text-muted\" href=\"/chinese-stroke-order-generator/\" data-toggle=\"tooltip\" title=\"Customize the stroke order diagrams\"><i class=\"fa fa-edit\" aria-hidden=\"true\"></i> Customize</a> <a class=\"btn btn-sm btn-link text-muted\" data-toggle=\"tooltip\" title=\"Save on Pinterest\" target=\"_blank\" data-pin-do=\"buttonPin\" data-pin-custom=\"true\" data-pin-save=\"true\" data-pin-shape=\"round\" href=\"https://www.pinterest.com/pin/create/button/?description=Stroke%20order%20image%20for%20Chinese%20character%20芝&amp;media=https://www.purpleculture.net/images/stroke/37721309.jpg\"><i class=\"fab fa-pinterest\" aria-hidden=\"true\" href=\"#\"></i> Pin it</a></span><br><img src=\"/images/stroke/37721309.jpg\" alt=\"Stroke order image for Chinese character 芝\" data-pin-do=\"buttonPin\"></div></div><div class=\"ml-auto hide\" id=\"char_ani_block\"><div id=\"char_flash_div\" class=\"charblock\"> <svg xmlns=\"http://www.w3.org/2000/svg\" id=\"char_flash_svg\"> <line x1=\"0\" y1=\"0\" x2=\"180\" y2=\"180\" stroke=\"#DDD\"></line> <line x1=\"180\" y1=\"0\" x2=\"0\" y2=\"180\" stroke=\"#DDD\"></line> <line x1=\"90\" y1=\"0\" x2=\"90\" y2=\"180\" stroke=\"#DDD\"></line> <line x1=\"0\" y1=\"90\" x2=\"180\" y2=\"90\" stroke=\"#DDD\"></line> <text id=\"char_count\" x=\"5\" y=\"175\" style=\"font-size: 14px;fill: #999;\"></text> </svg> </div> <div class=\"text-center pt-1\"></div></div></div><div class=\"clearBoth\"></div><div style=\"line-height: 1.6;\"><div><b>Example Words: </b></div><div class=\"swordlist\"><a class=\"sword\" href=\"/dictionary-details?word=%E8%8A%9D%E9%BA%BB\">芝麻</a> [ <a class=\"pinyin tone1 \" href=\"/mp3/zhi1.mp3\">zhī</a> <a class=\"pinyin tone5 \" href=\"/mp3/ma5.mp3\">ma</a> ]: sesame (seed)</div><div class=\"swordlist\"><a class=\"sword\" href=\"/dictionary-details?word=%E7%81%B5%E8%8A%9D\">灵芝</a> [ <a class=\"pinyin tone2 \" href=\"/mp3/ling2.mp3\">líng</a> <a class=\"pinyin tone1 \" href=\"/mp3/zhi1.mp3\">zhī</a> ]: lingzhi or reishi mushroom (Ganoderma lucidum)</div><div class=\"swordlist\"><a class=\"sword\" href=\"/dictionary-details?word=%E8%8A%9D%E9%BA%BB%E5%AE%98\">芝麻官</a> [ <a class=\"pinyin tone1 \" href=\"/mp3/zhi1.mp3\">zhī</a> <a class=\"pinyin tone5 \" href=\"/mp3/ma5.mp3\">ma</a> <a class=\"pinyin tone1 \" href=\"/mp3/guan1.mp3\">guān</a> ]: low ranking official; petty bureaucrat</div><div class=\"swordlist\"><a class=\"sword\" href=\"/dictionary-details?word=%E8%8A%9D%E9%BA%BB%E9%85%B1\">芝麻酱</a> [ <a class=\"pinyin tone1 \" href=\"/mp3/zhi1.mp3\">zhī</a> <a class=\"pinyin tone5 \" href=\"/mp3/ma5.mp3\">ma</a> <a class=\"pinyin tone4 \" href=\"/mp3/jiang4.mp3\">jiàng</a> ]: sesame paste</div><div class=\"swordlist\"><a class=\"sword\" href=\"/dictionary-details?word=%E8%8A%9D%E9%BA%BB%E6%B2%B9\">芝麻油</a> [ <a class=\"pinyin tone1 \" href=\"/mp3/zhi1.mp3\">zhī</a> <a class=\"pinyin tone5 \" href=\"/mp3/ma5.mp3\">ma</a> <a class=\"pinyin tone2 \" href=\"/mp3/you2.mp3\">yóu</a> ]: sesame oil</div><div class=\"swordlist\"><b>More: </b><a href=\"/chinese-english-dictionary/?word=芝*&amp;py=zhi1\" class=\"sword mr-1\">芝*</a> | <a href=\"/chinese-english-dictionary/?word=*芝*&amp;py=zhi1\" class=\"sword mr-1\">*芝</a> | <a href=\"/chinese-english-dictionary/?word=*芝*&amp;py=zhi1\" class=\"sword\">*芝*</a> </div></div>","hanziyuan":"<div class=\"etymology-nav\" id=\"&#x829D;\"><div class=\"alert alert-success m-0 etymology-alert\" role=\"alert\"></div><div class=\"row mx-0 bg-info row-eq-height border-top border-purple\" id=\"E08158\"><div class=\"col-md-3 col-sm-4 p-0\"><div class=\"p-1\"><p></p><p><b>Traditional in your browser 繁体字的浏览器显示:</b><span class=\"text-lg\">&#x829D;</span></p><p><b>Traditional in Unicode standard 繁体字的Unicode标准:</b><a href=\"https://www.unicode.org/cgi-bin/GetUnihanData.pl?codepoint=829D\" target=\"_blank\">U+829D</a><img src=\"https://www.unicode.org/cgi-bin/refglyph?24-829D\"/></p><p><b>Older traditional characters 旧繁体字/异体字:</b> Not exist </p><p><b>Simplified in your browser 简体字的浏览器显示:</b><span class=\"text-lg\">&#x829D;</span></p><p><b>Simplified in Unicode standard 简体字的Unicode标准:</b><a href=\"https://www.unicode.org/cgi-bin/GetUnihanData.pl?codepoint=829D\" target=\"_blank\">U+829D</a><img src=\"https://www.unicode.org/cgi-bin/refglyph?24-829D\"/></p><p><b>Main pronunciation 主要发音:</b> zh&#x12B;</p><p><b>Other pronunciations 其它发音:</b> Not exists.</p><p><b>Original meaning 本义:</b> Meaning sesame.</p><p><b>English senses 英语理解:</b> sessemy</p><p><b>Usage example 用法举例:</b> &#x829D;&#x9EBB; zh&#x12B; m&#xE1; (sesame)</p><p><b>Importance by frequency 常用频率:</b> 2100</p><p><b>Shuowen 说文解字:</b> &#x795E;&#x8278;&#x4E5F;&#x5F9E;&#x8278;&#x5F9E;&#x4E4B;</p><p class=\"pre-inline\"><b>Character decomposition 字形分解 <a href=\"https://dixin.github.io/Etymology/decomposition-of-chinese-character\" target=\"_blank\" title=\"Help: Decomposition of Chinese character\"></a>:</b><br/>Compound &#x829D; &#xD;&#xA;from grass-top &#x8279;&#x8278; c&#x1CE;o and &#xD;&#xA;phonetic foot-moving &#x4E4B;&#x37A2;&#x21CFF; zh&#x12B;.</p><p class=\"pre-inline\"><b>Decomposition notes 字形分解说明 <a href=\"https://dixin.github.io/Etymology/decomposition-of-chinese-character\" target=\"_blank\" title=\"Help: Decomposition of Chinese character\"></a>:</b><br/></p><p><b>Simplification rule <a target=\"_blank\" ></a>:</b></p><p class=\"pre-inline\"><b>Simplification rule explained <a target=\"_blank\" ></a>:</b><br/></p><p><b>Variant rule :</b></p><p class=\"pre-inline\"><b>Variant rule clarification <a target=\"_blank\" ></a>:</b><br/></p><p><b>Applied rules <a target=\"_blank\" ></a>:</b></p><p><b>New font rule <a target=\"_blank\" ></a>:</b></p><a target=\"_blank\" ><span ></span></a></div></div><div class=\"col-md-9 col-sm-8 etymology-result bg-primary p-1\" id=\"etymologyCharacters\"><h3><span ></span> </h3><p>There is no known oracle characters found. 没.</p><hr/><h3><span ></span> </h3><p>There is no known bronze characters found. 没.</p><hr/><h3><span ></span> Seal characters (1)</h3><ul class=\"list-inline list-unstyled\"><li class=\"text-center\"><img src=\"hanziyan-S00291.png\"/></li></ul><hr/><h3><span ></span> Liushutong characters (1)</h3><ul class=\"list-inline list-unstyled\"><li class=\"text-center\"><img src=\"hanziyan-L01047.png\"/></li></ul></div></div></div>","Tags":"jlpt1 jouyou8","rendered":"<span class=\"strokeorderkanji verylarge\">芝</span><span class=\"large strokeorderhanzi\">芝</span><span class=\"large\" style=\"font-family:yugothb\">芝</span>\n<hr>\n<div class=\"my-pinyin-image-container pinyin-number-1 pinyin-zhi\"><span></span><img><img></div>\n<div class=\"my-pinyin-tone\"><a href=\"allsetlearning-zhi1.mp3\" class=\"pinyin tone1\">zhī</a></div>\n<div class=\"my-pinyin-english\">Zoysia pungens</div>\n<div class=\"my-pinyin-ru\">Зойсия пунгенс</div>[anki:play:a:0]<br>\n<div class=\"tl\" id=\"russian\" style=\"color:#ff9e9e\">Trainchinese:</div><span class=\"trainchinese-pinyin\">zhī</span>: (<span class=\"trainchinese-type\">графема</span>) <span class=\"trainchinese-transl\">ароматная трава, пурпурный гриб, символизирующий благородство</span>\n<div class=\"tl rustl\" id=\"yarxi\">Yarxi: газон</div>\n<div class=\"tl\" id=\"meaning\">Meaning: turf, lawn</div>\n<hr>\n<div class=\"tiny\">\n  <font color=\"#e20096\">Lawn</font>\n</div>\n<hr>\n<div>turf | дерн</div>\n<hr>\n<div>KKLC</div>\n<div style=\"display:flex\">\n  <div style=\"width:100%\">LAWN GRASS</div>\n  <div style=\"width:100%\">газонные травы</div>\n</div>\n<hr>\n<div>KANJIDIC</div>\n<div style=\"display:flex\">\n  <div style=\"width:100%\">turf, lawn</div>\n  <div style=\"width:100%\">дерн, лужайка</div>\n</div>\n<hr>Links: <a href=\"aedict://芝\">aedict</a> | <a href=\"http://jisho.org/kanji/details/芝\">jisho</a> | <a href=\"http://kanji.koohii.com/study/kanji/芝\">koohii</a> | <a href=\"https://hanziyuan.net/#芝\">hanziyuan</a> | <a href=\"https://www.kanshudo.com/kanji/芝\">kanshudo</a> | <a href=\"https://en.m.wiktionary.org/wiki/芝\">wiktionary</a> | <a href=\"https://www.purpleculture.net/dictionary_details/?word=芝\">purpleculture</a> | <a href=\"http://rtega.be/chmn/?c=芝\">rtega</a> | <a href=\"https://www.trainchinese.com/v2/search.php?searchWord=芝&tcLanguage=ru\">trainchinese</a> | <a href=\"https://bkrs.info/slovo.php?ch=芝&tcLanguage=ru\">bkrs</a> | <a href=\"http://humanum.arts.cuhk.edu.hk/Lexis/lexi-mf/search.php?word=芝\">humanum</a> | <a href=\"https://baike.baidu.com/item/芝\">Baido</a> | <a href=\"https://www.yw11.com/zidian/index/search/芝\">yw11</a> | <a href=\"plecoapi://x-callback-url/s?q=芝\">Pleco Search</a> | <a href=\"plecoapi://x-callback-url/s?mode=df&hw=芝&sec=dict&x-source=Anki\">Pleco</a>\n<hr>\n<div id=\"ch_with_same_pronounciation\">\n  <div class=\"pinyin\">zhi1</div>\n  <div class=\"same-pronounciation\">\n    <div class=\"row row-hsk-2\"><span class=\"key\">HSK 2</span>: <span class=\"kanji\">知</span></div>\n    <div class=\"row row-hsk-3\"><span class=\"key\">HSK 3</span>: <span class=\"kanji\">只</span>,<span class=\"kanji\">隻</span></div>\n    <div class=\"row row-hsk-4\"><span class=\"key\">HSK 4</span>: <span class=\"kanji\">之</span>,<span class=\"kanji\">汁</span></div>\n    <div class=\"row row-hsk-5\"><span class=\"key\">HSK 5</span>: <span class=\"kanji\">支</span>,<span class=\"kanji\">织</span></div>\n    <div class=\"row row-hsk-6\"><span class=\"key\">HSK 6</span>: <span class=\"kanji\">枝</span>,<span class=\"kanji\">氏</span>,<span class=\"kanji\">脂</span>,<span class=\"kanji\">肢</span></div>\n  </div>\n</div>\n<hr>\n<div id=\"rtega_mnemonic\">\n  <table>\n    <tr>\n      <td>芝芝<a href=\"http://rtega.be/chmn/?reversec=芝\">R</a><a href=\"http://rtega.be/chmn/index.php?submit=2781\">S</a></td>\n      <td></td>\n      <td>turf, lawn, purplish fungus symbolizing nobility, kind of fragrant herb</td>\n      <td>\n        <ul>\n          <li title=\"Reinaert Albrecht\">grass <a href=\"http://rtega.be/chmn/?c=艹\">艹</a> shooting out of the ground <a href=\"http://rtega.be/chmn/?c=之\">之</a></li>\n        </ul>\n      </td>\n      <td></td>\n    </tr>\n  </table>\n</div>\n<hr>\n<div id=\"purpleculture_info\">\n  <div>\n    <div><b>Chinese Definition:</b>\n      <div><b>Pictophonetic</b>: <span class=\"semantic\"><a class=\"dictips\">之</a></span> indicates the sound; <span class=\"phonetic\"><a class=\"dictips\">艹</a></span> (plant) conveys the meaning.</div>\n    </div>\n  </div>\n</div>\n<div id=\"purpleculture_tree\">\n  <div class=\"tree\">\n    <ul>\n      <li><span class=\"str_def\">⿱</span> <span class=\"str_desc\">Above to below</span>\n        <ul>\n          <li><span class=\"str_def\"><a class=\"dictips\">艹</a></span> <span class=\"str_py\">[ <a href=\"allsetlearning-cao3.mp3\" class=\"pinyin tone3\">cǎo</a> ]</span> <span class=\"str_desc\">grass, weed, plant, herb</span></li>\n          <li><span class=\"str_def\"><a class=\"dictips\">之</a></span> <span class=\"str_py\">[ <a href=\"allsetlearning-zhi1.mp3\" class=\"pinyin tone1\">zhī</a> ]</span> <span class=\"str_desc\">marks preceding phrase as modifier of following phrase; it, him her, them; to go to</span></li>\n        </ul>\n      </li>\n    </ul>\n  </div>\n</div>\n<hr><span id=\"purpleculture_examples\">①(灵芝)见“(芝兰)“芝”和“。<br>②灵”。兰”，古书上指两种香草，喻德行的高尚或友情、环境的美好等，如“芝芝之室”、“芝芝玉树”。<br><a href=\"https://www.purpleculture.net/dictionary-details?word=%E8%8A%9D%E9%BA%BB\" class=\"sword\">芝麻</a> [ <a href=\"allsetlearning-zhi1.mp3\" class=\"pinyin tone1\">zhī</a> <a href=\"allsetlearning-ma5.mp3\" class=\"pinyin tone5\">ma</a> ]: sesame (seed)<br><a href=\"https://www.purpleculture.net/dictionary-details?word=%E8%8A%9D%E9%BA%BB%E5%AE%98\" class=\"sword\">芝麻官</a> [ <a href=\"allsetlearning-zhi1.mp3\" class=\"pinyin tone1\">zhī</a> <a href=\"allsetlearning-ma5.mp3\" class=\"pinyin tone5\">ma</a> <a href=\"allsetlearning-guan1.mp3\" class=\"pinyin tone1\">guān</a> ]: low ranking official; petty bureaucrat<br><a href=\"https://www.purpleculture.net/dictionary-details?word=%E8%8A%9D%E9%BA%BB%E9%85%B1\" class=\"sword\">芝麻酱</a> [ <a href=\"allsetlearning-zhi1.mp3\" class=\"pinyin tone1\">zhī</a> <a href=\"allsetlearning-ma5.mp3\" class=\"pinyin tone5\">ma</a> <a href=\"allsetlearning-jiang4.mp3\" class=\"pinyin tone4\">jiàng</a> ]: sesame paste<br><a href=\"https://www.purpleculture.net/dictionary-details?word=%E8%8A%9D%E9%BA%BB%E6%B2%B9\" class=\"sword\">芝麻油</a> [ <a href=\"allsetlearning-zhi1.mp3\" class=\"pinyin tone1\">zhī</a> <a href=\"allsetlearning-ma5.mp3\" class=\"pinyin tone5\">ma</a> <a href=\"allsetlearning-you2.mp3\" class=\"pinyin tone2\">yóu</a> ]: sesame oil</span>\n<hr>\n<div>\n  <div><b>Chinese Definition:</b>\n    <div><b>Pictophonetic</b>: <span class=\"semantic\"><a class=\"dictips\">之</a></span> indicates the sound; <span class=\"phonetic\"><a class=\"dictips\">艹</a></span> (plant) conveys the meaning.</div>\n  </div>\n</div>\n<div>Freq: 2150</div>\n<hr><span><span style=\"color:#1ce63d\">Kanshudo mnemonic:</span>of (<a href=\"/kanji/%E4%B9%8B\">之</a>) grass (<a href=\"/kanji/%E8%89%B9\">艹</a>) = a lawn</span>\n<div>On-Yomi: <span class=\"japanese\" style=\"color:red\">シ</span></div>\n<div>Kun-Yomi: <span class=\"japanese\" style=\"color:#9ab5ff\">しば</span></div>\n<div><img src=\"E88A9D.png\"></div>\n<div id=\"heisig_constituent\"><span style=\"color:tomato\">Heisig constituents</span>: turf, flowers, of, Zorro, building blocks, zig-zag</div>\n<div><span style=\"color:tomato\">Heisig</span>: Flowers . . . building blocks.</div>\n<div><span style=\"color:tomato\">Chinese</span>: Zorro, with a flower between his teeth for the ladies, defends his turf where he harvests black sesame. \"This is my turf! And this...is for the lady, as he hands her some Chinese black sesame pudding.\".</div>\n<hr><span><span style=\"color:tomato\">koohii1</span>: Artificial turf made easy: flowers stuck on top of building blocks that you can place anywhere.</span>\n<hr><span><span style=\"color:tomato\">koohii2</span>: Zorro, with a flower between his teeth for the ladies, defends his turf against evildoers. \"This is my turf! And this...is for the lady.\".</span>\n<hr>\n<div><span style=\"color:#f5950f\">Meaning:</span> sesame<br><span style=\"color:#f5950f\">Story:</span> Zorro, with a flower between his teeth for the ladies, defends his turf where he harvests black sesame. \"This is my turf! And this...is for the lady, as he hands her some Chinese black sesame pudding.\".<br><span style=\"color:#f5950f\">Kind:</span> both<br><img src=\"lf_33437.gif\"></div>\n<div>\n  <hr><span>Lesson: 32&nbsp;</span><span>frameNoV4: 1216&nbsp;</span><span>frameNoV6: 1301&nbsp;</span><span>Strokes: 6&nbsp;</span><span>Jouyou Grade: JH&nbsp;</span><span>JLPT: 1</span>\n</div>\n<hr><span id=\"jp_example_words\">芝(しば): lawn, sod, turf<br>芝居(しばい): play, drama<br>芝生(しばふ): lawn</span>\n<hr><img src=\"http://humanum.arts.cuhk.edu.hk/Lexis/lexi-mf/kangxiArchaic.php?hash=ba5cf909d016d95c506b88a5335ad8bf\"><br>\n<div class=\"two_children__horiz_even\">\n  <div id=\"humanum_full_description\">從「 艸 」，「 之 」聲。本義是靈芝草，一種菌類植物。古人認為是瑞草。《說文》：「芝，神艸也。从艸从之。」《玉篇．草部》：「芝，瑞草。」如《史記．孝武本紀》：「甘泉防生芝九莖，赦天下，毋有復作。」《論衡．驗符》：「芝草延年，仙者所食。」 「 芝 」又表示白芷，是一種香草。如《文選．陸士衡〈歎逝賦〉》：「信松茂而柏悅，嗟芝焚而蕙歎。」李周翰注：「芝，香草也。」古書裡常以「芝蘭」連用，如《孔子家語．在厄》：「且芝蘭生於深林，不以無人而不芳；君子修道立德，不為窮困而敗節。」</div>\n  <div id=\"humanum_full_description_en\">From \" 艸\", \" Zhi\" sound. The original meaning is Ganoderma lucidum, a fungus plant. The ancients thought it was Seocho. \"Said Wen\": \"Zhi, the gods are also. From the chasing to it.\" \"Jade chapter. Caobu\": \"Zhi, Seocho.\" Such as \"Historical Records. \"Xiaowu Benji\": \"The nine stems of Ganquan Fangshengzhi, forgiving the world, there is no duplication.\" \"Lun Heng. Verification of Symbols: \"Zhi grass extends the year, eaten by immortals.\" \" Zhi\" also means Baizhi, which is a kind of vanilla. Such as \"Selected Works. Lu Shiheng's \"Sigh for the Death\": \"Believe in the pine and luxuriant but Park Hyatt, sigh the zhi burn and sigh.\" Li Zhouhan's note: \"Zhi, vanilla.\" In ancient books, \"Zhi Lan\" is often used together, such as \"Confucius' Family Language. \"Zai E\": \"Also, Zhilan was born in the deep forest, and he does not think that there is no one but is not fragrant; a gentleman cultivates virtue and does not lose his life for poverty.\"</div>\n</div>\n<div id=\"hanziyuan\">\n  <div class=\"etymology-nav\" id=\"&#x829D;\">\n    <div class=\"alert alert-success etymology-alert m-0\" role=\"alert\"></div>\n    <div class=\"row bg-info border-purple border-top mx-0 row-eq-height\" id=\"E08158\">\n      <div class=\"col-md-3 col-sm-4 p-0\">\n        <div class=\"p-1\">\n          <p></p>\n          <p><b>Traditional in your browser 繁体字的浏览器显示:</b><span class=\"text-lg\">&#x829D;</span></p>\n          <p><b>Traditional in Unicode standard 繁体字的Unicode标准:</b><a href=\"https://www.unicode.org/cgi-bin/GetUnihanData.pl?codepoint=829D\" target=\"_blank\">U+829D</a><img src=\"https://www.unicode.org/cgi-bin/refglyph?24-829D\"></p>\n          <p><b>Older traditional characters 旧繁体字/异体字:</b> Not exist</p>\n          <p><b>Simplified in your browser 简体字的浏览器显示:</b><span class=\"text-lg\">&#x829D;</span></p>\n          <p><b>Simplified in Unicode standard 简体字的Unicode标准:</b><a href=\"https://www.unicode.org/cgi-bin/GetUnihanData.pl?codepoint=829D\" target=\"_blank\">U+829D</a><img src=\"https://www.unicode.org/cgi-bin/refglyph?24-829D\"></p>\n          <p><b>Main pronunciation 主要发音:</b> zh&#x12B;</p>\n          <p><b>Other pronunciations 其它发音:</b> Not exists.</p>\n          <p><b>Original meaning 本义:</b> Meaning sesame.</p>\n          <p><b>English senses 英语理解:</b> sessemy</p>\n          <p><b>Usage example 用法举例:</b> &#x829D;&#x9EBB; zh&#x12B; m&#xE1; (sesame)</p>\n          <p><b>Importance by frequency 常用频率:</b> 2100</p>\n          <p><b>Shuowen 说文解字:</b> &#x795E;&#x8278;&#x4E5F;&#x5F9E;&#x8278;&#x5F9E;&#x4E4B;</p>\n          <p class=\"pre-inline\"><b>Character decomposition 字形分解 <a href=\"https://dixin.github.io/Etymology/decomposition-of-chinese-character\" target=\"_blank\" title=\"Help: Decomposition of Chinese character\"></a>:</b><br>Compound &#x829D; &#xD;&#xA;from grass-top &#x8279;&#x8278; c&#x1CE;o and &#xD;&#xA;phonetic foot-moving &#x4E4B;&#x37A2;&#x21CFF; zh&#x12B;.</p>\n          <p class=\"pre-inline\"><b>Decomposition notes 字形分解说明 <a href=\"https://dixin.github.io/Etymology/decomposition-of-chinese-character\" target=\"_blank\" title=\"Help: Decomposition of Chinese character\"></a>:</b><br></p>\n          <p><b>Simplification rule <a target=\"_blank\"></a>:</b></p>\n          <p class=\"pre-inline\"><b>Simplification rule explained <a target=\"_blank\"></a>:</b><br></p>\n          <p><b>Variant rule :</b></p>\n          <p class=\"pre-inline\"><b>Variant rule clarification <a target=\"_blank\"></a>:</b><br></p>\n          <p><b>Applied rules <a target=\"_blank\"></a>:</b></p>\n          <p><b>New font rule <a target=\"_blank\"></a>:</b></p><a target=\"_blank\"><span></span></a>\n        </div>\n      </div>\n      <div class=\"p-1 bg-primary col-md-9 col-sm-8 etymology-result\" id=\"etymologyCharacters\">\n        <h3><span></span></h3>\n        <p>There is no known oracle characters found. 没.</p>\n        <hr>\n        <h3><span></span></h3>\n        <p>There is no known bronze characters found. 没.</p>\n        <hr>\n        <h3><span></span> Seal characters (1)</h3>\n        <ul class=\"list-inline list-unstyled\">\n          <li class=\"text-center\"><img src=\"hanziyan-S00291.png\"></li>\n        </ul>\n        <hr>\n        <h3><span></span> Liushutong characters (1)</h3>\n        <ul class=\"list-inline list-unstyled\">\n          <li class=\"text-center\"><img src=\"hanziyan-L01047.png\"></li>\n        </ul>\n      </div>\n    </div>\n  </div>\n</div>\n<div class=\"two_children__horiz_even\">\n  <div id=\"yw11\">\n    <h4><span>芝</span>字的基本解释</h4>\n    <div>\n      <p>芝<br>zhī<br>〔灵芝〕见“<br>〔芝兰〕“芝”和“<br>灵”。兰”，古书上指两种香草，喻德行的高尚或友情、环境的美好等，如“芝芝之室”、“芝芝玉树”。<br><br></p>\n    </div>\n    <div><span>芝</span>字的汉语字典释义</div>\n    <div>\n      <p>[①]［zhī］<br>［《廣韻》止而切，平之，章。］<br>(1)芝草。菌类植物，生枯木上，有青、赤、黄、白、黑、紫等色。古以为瑞草，服之可以成仙，故又名灵芝。<br>(2)指形如菌盖的东西。多指车盖。<br>(3)通“芷”。香草。参见“芝蘭”。</p>\n    </div>\n    <div><span>芝</span>字的康熙字典解释</div>\n    <div>\n      <p>【申集上】【艸字部】　芝； 康熙笔画：10； 页码：<a href=\"https://images.yw11.com/kangxi/1019.gif\" target=\"_blank\"><span>页1019第15</span></a><br>【唐韻】止而切【集韻】【韻會】眞而切【正韻】旨而切，?音之。【說文】神草也。【本草】有靑赤黃白黑紫六色。【註】芝爲瑞草，服之神仙。【王充·論衡】芝生於土，土氣和，故芝草生。【瑞應圖】王者敬事耆老，不失舊故，則芝草生。【白虎通】德至山陵，則景雲出，芝實茂。　又【禮·內則】芝栭蔆椇。　又【揚雄·甘泉賦】于是乗輿，乃登夫鳳凰兮而翳華芝。【註】華芝，華蓋也。　【六書略】隷作㞢，象芝出地。</p>\n    </div>\n    <div><span>芝</span>字的源字形</div>\n    <div>\n      <p></p>\n    </div>\n    <div><span>芝</span>字的起名意思</div>\n    <div>\n      <p>：一种瑞草，取名灵芝，又名芝兰的香草。灵芝意为能使人延年益寿、长生不老、芝字多为人名所用。</p>\n    </div>\n  </div>\n  <div id=\"yw11_en_transl\">Shiba<br>Basic explanation of words<br>Shiba<br>zhī<br>[Ganoderma lucidum] see \"<br>[芝兰] \"芝\" and \"<br>\"Ling\". Lan\" in ancient books refers to two kinds of herbs, such as \"Zhizhi Room\" and \"Zhizhi Yushu\".<br>Shiba<br>Chinese dictionary definition of words<br>[①]［zhī］<br>[\"Guangyun\" stop and cut, level it, chapter. ]<br>(1) Chi grass. Fungus plants are green, red, yellow, white, black, purple and other colors on dead wood. In ancient times, it was thought that Seocho could become an immortal after taking it, so it was also called Lingzhi.<br>(2) Refers to something shaped like a fungus cap. Multi-finger car cover.<br>(3) Through \"zhi\". vanilla. See \"Chi Lan\".<br>Shiba<br>Kangxi dictionary interpretation of words<br>[Shen Ji 1] [Department of Jian Zi] 　芝; Kangxi strokes: 10; page number: page 1019 15<br>[Tang Yun] Stop and cut [Ji Yun] [Rhyme] Straight and cut [Zheng Yun] Cut with purpose,? Sound of. [Said the text] God grass is also. 【Materia Medica】There are six colors of red, yellow, white, black and purple. [Note] Zhi is Seocho, the god of service. [Wang Chong·Lunheng] Zhi was born in the soil, rustic and harmonious, so Zhicao was born. [Ruiying map] The king respects the elderly, and does not lose the old past, then Zhicao is born. 【Baihutong】From Germany to the mountain tombs, there will be scenery and clouds, and Zhishimao.　[Li·Nei Ze] Zhi Shi Ling Yu.　[Yang Xiong·Ganquan Fu] So Cheng Yu, it was Huazhi who came to the phoenix as her husband. [Note] Huazhi, Huagai also.　【Liu Shu Lute】Li Zuo 㞢, Xiang Zhi came out of the land.<br>Shiba<br>Source glyph<br>Shiba<br>Name meaning<br>: A kind of Seocho, named Ganoderma lucidum, also known as Zhilan's vanilla. Ganoderma lucidum means longevity, longevity, and immortality. The characters of zhizhi are mostly used by people's names.</div>\n</div>\n<div><a href=\"https://images.yw11.com/zixing/zi148276452114334.png\" target=\"_blank\"><object data=\"https://images.yw11.com/zixing/zi148276452114334.png\" type=\"image/png\"><img src=\"yw11-zixing-zi148276452114334.png\"></object></a></div>\n<div class=\"two_children__horiz_even\">\n  <div id=\"yw11_image_chinese\">芝<br>形声字。艸(+)表意,篆书形体像草,表示芝是植物;之(zhi)表声,之有往义,灵芝古称仙草,生长在深山密林中,要<br>前往寻找才能获得。本义是灵芝。又指另一种香草,即白芷。<br>①灵芝,一种菌类植物可供药用。2古书上指白芷:~兰。<br>~艾 ~兰 ~麻 兰~ 灵~ 紫~<br>zhī<br>, 芝。<br>隶<br>「楷</div>\n  <div id=\"yw11_image_ru_transl\">Шиба<br>Пиктофонетические символы.<br>Знак 艸 (+) означает, что шрифт печати подобен траве, что означает, что чжи - это растение; его (чжи) означает, что оно имеет смысл. Ganoderma lucidum в древние времена называлась волшебной травой. Она растет в глубоких горах. и густые леса, и получить его можно только ища.<br>Первоначальное значение - Ganoderma lucidum.<br>Это также относится к другому виду ванили, а именно к Angelica dahurica.<br>① Ganoderma lucidum - грибное растение, которое можно использовать в лечебных целях.<br>2 В древней книге говорится об Анжелике Дахурике: ~ Лан.<br>~ Ай ~ Лан ~ Маран ~ Линг ~ Фиолетовый ~<br>, Чжи.<br>писец<br>\"Кай</div>\n</div>\n<hr>\n<div id=\"bkrs_pinyin\">zhī</div>\n<div id=\"bkrs_transl\">\n  <div><strong>I</strong> <i>сущ.</i></div>\n  <div>1) <i>сокр.</i> (<span class=\"paragraph\">вм.</span> 灵芝) трутовик, древесный гриб (<i>символ долголетия, счастья</i>)</div>\n  <div>2) зонтик; верх (<i>экипажа</i>)</div>\n  <div>3) <i>вм.</i> 芷 (<i>борщевик; ароматная трава</i>)</div>\n  <div>4) <span class=\"paragraph\">бот.</span> цойсия японская (<i>Zoysia pungens</i>)</div>\n  <div><strong>II</strong> <i>собств.</i></div>\n  <div>Чжи (<i>фамилия</i>)</div>\n</div>\n<hr>\n<hr><span class=\"text\"><b>Radicals:</b></span>\n<font color=\"#0a9ce6\"><span class=\"hiragana\"><b>艹</b></span> <span class=\"radical_icons\"></span></font>&nbsp;<span class=\"text\">(flowers, hills)</span><br><u><span class=\"tiny\"><b>Meaning Mnemonic</b></span></u><br><span class=\"tiny\">There are <span class=\"radical-highlight\" rel=\"tooltip\" title=\"Radical\">flowers</span> and <span class=\"radical-highlight\" rel=\"tooltip\" title=\"Radical\">hills</span> in your front <span class=\"kanji-highlight\" rel=\"tooltip\" title=\"Kanji\">lawn</span>. Your lawn is pretty big and it is covered with both flowers and hills. It’s very pretty.<br><i>Imagine walking through your lawn and smelling all the flowers as you travel over the rolling hills. What a delightful lawn this is.</i></span><br><u><span class=\"tiny\"><b>Reading Mnemonic</b></span></u><br><span class=\"tiny\">You are the proud owner of a <span class=\"reading-highlight\" rel=\"tooltip\" title=\"Reading\">Shiba</span> (<span lang=\"ja\">しば</span>) Inu, y’know, the Japanese dog? Well, this Shiba Inu of yours loves to run around in your <span class=\"kanji-highlight\" rel=\"tooltip\" title=\"Kanji\">lawn</span> and through the flowers and over the hills. This is the perfect lawn for your Shiba.<br><i>Look at your little Shiba running through the lawn all happy and elated. Hear him barking as he zooms up and down each hill.</i></span><br>\n<p><a href=\"https://www.mdbg.net/chinese/dictionary?page=worddict&wdrst=0&wdqtm=0&wdqcham=1&wdqt=\">MDBG</a> | <a href=\"https://bkrs.info/slovo.php?ch=芝\">BKRS</a> | <a href=\"https://dictionary.writtenchinese.com/#sk=芝&svt=pinyin\">WriCh</a> | <a href=\"http://www.qianyix.com/words/index.php?q=芝\">Qianyix</a> | <a href=\"https://www.yellowbridge.com/chinese/sentsearch.php?word=芝\">YBridge</a> | <a href=\"http://cca.xingtanlu.cn/?action=page&pid=8&do=search&name=芝\">Collocs</a> | <a href=\"https://characterpop.com/explode/芝\">ChPop</a> | <a href=\"https://visualchinesesearch.com/?query=芝\">SimCh</a> | <a href=\"http://www.hanzicraft.com/character/芝\">Stats</a> | <a href=\"https://www.google.com.au/search?q=芝&tbm=isch\">Google Images</a> | <a href=\"https://namakajiri.net/kanjigen/#芝\">Char lookup site</a></p><br><span class=\"tiny\">Examples: <span class=\"japanese\">芝 (しば)</span></span>\n<div class=\"notes optional small\">亠 (крышка), 艾 (мокса)</div>\n<div class=\"notes optional\">Также: 芝居 (しばい театральная постановка);</div>","glyphs":[{"glyph":"艹","pinyins":["cao3"]},{"glyph":"之","pinyins":["zhi1"]}]}