{"kanji":"饫","purpleculture_pinyin":"<div class=\"my-pinyin-image-container pinyin-yu pinyin-number-4\"><span></span><img><img></div>   <div class=\"my-pinyin-tone\"><a class=\"pinyin tone4 \" href=\"https://www.purpleculture.net/mp3/yu4.mp3\">yù</a></div>   <div class=\"my-pinyin-english\">full (as of eating)</div>   <div class=\"my-pinyin-ru\">полный (после еды)</div>","chinese_junda_freq_ierogliph_number":"5141","purpleculture_info":"<div><div ><div > <span class=\"tc\">(Trad.: 飫)</span></div> <div><b>Pictophonetic</b>: <span class=\"semantic\"><a class=\"dictips\">夭</a></span> indicates the sound; <span class=\"phonetic\"><a class=\"dictips\">饣</a></span> (eat) conveys the meaning.</div></div></div>","purpleculture_examples":"<a class=\"sword\" href=\"https://www.purpleculture.net/dictionary-details?word=%E9%A5%AB%E7%94%98%E9%A4%8D%E8%82%A5\">饫甘餍肥</a> [ <a class=\"pinyin tone4 \" href=\"https://www.purpleculture.net/mp3/yu4.mp3\">yù</a> <a class=\"pinyin tone1 \" href=\"https://www.purpleculture.net/mp3/gan1.mp3\">gān</a> <a class=\"pinyin tone4 \" href=\"https://www.purpleculture.net/mp3/yan4.mp3\">yàn</a> <a class=\"pinyin tone2 \" href=\"https://www.purpleculture.net/mp3/fei2.mp3\">féi</a> ]: to live off the fat of the land (idiom); to have a luxurious lifestyle","purpleculture_tree":"<div class=\"tree\"><ul><li><span class=\"str_def\">⿰</span> <span class=\"str_desc\">Left to right</span><ul><li><span class=\"str_def\"><a class=\"dictips\">饣</a></span> <span class=\"str_py\">[ <a class=\"pinyin tone2 \" href=\"https://www.purpleculture.net/mp3/shi2.mp3\">shí</a> ]</span> <span class=\"str_desc\">food; to eat</span></li><li><span class=\"str_def\"><a class=\"dictips\">夭</a></span> <span class=\"str_py\">[ <a class=\"pinyin tone1 \" href=\"https://www.purpleculture.net/mp3/yao1.mp3\">yāo</a> ]</span> <span class=\"str_desc\">young, energetic; to die young</span></li></ul></li></ul></div>","purpleculture_img":"https://www.purpleculture.net/images/stroke/63916646.jpg","Ru_trainchinese":"<span class=\"trainchinese-pinyin\">yù</span>: (<span class=\"trainchinese-type\">графема</span>) <span class=\"trainchinese-transl\">(книжн.) наесться до отвала, насытиться</span>","_purpleculture_dictionary_orig_full":"<div class=\"d-flex\"><div style=\"line-height:1.6\"><div id=\"sen0\"><ruby class=\"mainsc\">饫</ruby> <span class=\"tc\">(Trad.: 飫)</span><div class=\"btn-group px-2\"><a class=\"btn btn-default px-1 text-muted\" href=\"/mp3/yu4.mp3\"> <i class=\"fas fa-volume-up\" aria-hidden=\"true\" data-toggle=\"tooltip\" title=\"Speak\"></i></a> </div></div><b>Pinyin: </b> <a class=\"pinyin tone4 \" href=\"/mp3/yu4.mp3\">yù</a><br><b>English Definition: </b><span class=\"en\">full (as of eating)</span><br><div class=\"clearBoth\"></div><div class=\"charstr\"><b>Total strokes:</b> 7; <b>Radical:</b> <a href=\"javascript:;\" class=\"radicaltips tips\" title=\"食&nbsp;(飠,饣) [ <a class='pinyin tone2 ' href='/mp3/shi2.mp3'>shí</a>] <a href='radical/?id=184' class='ml-2'> <i class='fas fa-external-link-alt text-muted'></i></a> <br><br>eat\">食</a></div><div><b>Pictophonetic</b>: <span class=\"semantic\"><a href=\"javascript:\" class=\"dictips\" title=\"loading...\">夭</a></span> indicates the sound; <span class=\"phonetic\"><a href=\"javascript:\" class=\"dictips\" title=\"loading...\">饣</a></span> (eat) conveys the meaning.</div><div><b>Character Formation:</b></div><div class=\"tree\"><ul><li><span class=\"str_def\">⿰</span> <span class=\"str_desc\">Left to right</span><ul><li><span class=\"str_def\"><a href=\"javascript:\" class=\"dictips\" title=\"loading...\">饣</a></span> <span class=\"str_py\">[ <a class=\"pinyin tone2 \" href=\"/mp3/shi2.mp3\">shí</a> ]</span> <span class=\"str_desc\">food; to eat</span></li><li><span class=\"str_def\"><a href=\"javascript:\" class=\"dictips\" title=\"loading...\">夭</a></span> <span class=\"str_py\">[ <a class=\"pinyin tone1 \" href=\"/mp3/yao1.mp3\">yāo</a> ]</span> <span class=\"str_desc\">young, energetic; to die young</span></li></ul></li></ul></div><div class=\"py-2\"><b>Step by Step Stroke Sequence:</b><span id=\"stroke_tool\"><a class=\"btn btn-sm btn-link text-muted\" href=\"/images/stroke/63916646.jpg\" download=\"stroke_sequence.jpg\" data-toggle=\"tooltip\" title=\"Download the chart\"><i class=\"fa fa-download\" aria-hidden=\"true\"></i> Download</a> <a class=\"btn btn-sm btn-link text-muted\" href=\"/chinese-stroke-order-generator/\" data-toggle=\"tooltip\" title=\"Customize the stroke order diagrams\"><i class=\"fa fa-edit\" aria-hidden=\"true\"></i> Customize</a> <a class=\"btn btn-sm btn-link text-muted\" data-toggle=\"tooltip\" title=\"Save on Pinterest\" target=\"_blank\" data-pin-do=\"buttonPin\" data-pin-custom=\"true\" data-pin-save=\"true\" data-pin-shape=\"round\" href=\"https://www.pinterest.com/pin/create/button/?description=Stroke%20order%20image%20for%20Chinese%20character%20饫&amp;media=https://www.purpleculture.net/images/stroke/63916646.jpg\"><i class=\"fab fa-pinterest\" aria-hidden=\"true\" href=\"#\"></i> Pin it</a></span><br><img src=\"/images/stroke/63916646.jpg\" alt=\"Stroke order image for Chinese character 饫\" data-pin-do=\"buttonPin\"></div></div><div class=\"ml-auto hide\" id=\"char_ani_block\"><div id=\"char_flash_div\" class=\"charblock\"> <svg xmlns=\"http://www.w3.org/2000/svg\" id=\"char_flash_svg\"> <line x1=\"0\" y1=\"0\" x2=\"180\" y2=\"180\" stroke=\"#DDD\"></line> <line x1=\"180\" y1=\"0\" x2=\"0\" y2=\"180\" stroke=\"#DDD\"></line> <line x1=\"90\" y1=\"0\" x2=\"90\" y2=\"180\" stroke=\"#DDD\"></line> <line x1=\"0\" y1=\"90\" x2=\"180\" y2=\"90\" stroke=\"#DDD\"></line> <text id=\"char_count\" x=\"5\" y=\"175\" style=\"font-size: 14px;fill: #999;\"></text> </svg> </div> <div class=\"text-center pt-1\"></div></div></div><div class=\"clearBoth\"></div><div style=\"line-height: 1.6;\"><div><b>Example Words: </b></div><div class=\"swordlist\"><a class=\"sword\" href=\"/dictionary-details?word=%E9%A5%AB%E7%94%98%E9%A4%8D%E8%82%A5\">饫甘餍肥</a> [ <a class=\"pinyin tone4 \" href=\"/mp3/yu4.mp3\">yù</a> <a class=\"pinyin tone1 \" href=\"/mp3/gan1.mp3\">gān</a> <a class=\"pinyin tone4 \" href=\"/mp3/yan4.mp3\">yàn</a> <a class=\"pinyin tone2 \" href=\"/mp3/fei2.mp3\">féi</a> ]: to live off the fat of the land (idiom); to have a luxurious lifestyle</div><div class=\"swordlist\"><b>More: </b><a href=\"/chinese-english-dictionary/?word=饫*&amp;py=yu4\" class=\"sword mr-1\">饫*</a> | <a href=\"/chinese-english-dictionary/?word=*饫*&amp;py=yu4\" class=\"sword mr-1\">*饫</a> | <a href=\"/chinese-english-dictionary/?word=*饫*&amp;py=yu4\" class=\"sword\">*饫*</a> </div></div>","hanziyuan":"<div class=\"etymology-nav\" id=\"&#x996B;\"><div class=\"alert alert-success m-0 etymology-alert\" role=\"alert\"></div><div class=\"row mx-0 bg-info row-eq-height border-top border-purple\" id=\"E07729\"><div class=\"col-md-3 col-sm-4 p-0\"><div class=\"p-1\"><p></p><p><b>Traditional in your browser 繁体字的浏览器显示:</b><span class=\"text-lg\">&#x98EB;</span></p><p><b>Traditional in Unicode standard 繁体字的Unicode标准:</b><a href=\"https://www.unicode.org/cgi-bin/GetUnihanData.pl?codepoint=98EB\" target=\"_blank\">U+98EB</a><img src=\"https://www.unicode.org/cgi-bin/refglyph?24-98EB\"/></p><p><b>Older traditional characters 旧繁体字/异体字:</b> Not exist </p><p><b>Simplified in your browser 简体字的浏览器显示:</b><span class=\"text-lg\">&#x996B;</span></p><p><b>Simplified in Unicode standard 简体字的Unicode标准:</b><a href=\"https://www.unicode.org/cgi-bin/GetUnihanData.pl?codepoint=996B\" target=\"_blank\">U+996B</a><img src=\"https://www.unicode.org/cgi-bin/refglyph?24-996B\"/></p><p><b>Main pronunciation 主要发音:</b> y&#xF9;</p><p><b>Other pronunciations 其它发音:</b> Not exists.</p><p><b>Original meaning 本义:</b> Meaning surfeited, satiated; confer</p><p><b>English senses 英语理解:</b></p><p><b>Usage example 用法举例:</b></p><p><b>Importance by frequency 常用频率:</b></p><p><b>Shuowen 说文解字:</b></p><p class=\"pre-inline\"><b>Character decomposition 字形分解 <a href=\"https://dixin.github.io/Etymology/decomposition-of-chinese-character\" target=\"_blank\" title=\"Help: Decomposition of Chinese character\"></a>:</b><br/>Compound &#x98EB; &#xD;&#xA;from mouth-eating (&#x9963;)&#x98E0;&#x98DF; sh&#xED; and &#xD;&#xA;phonetic young-person &#x592D; y&#x101;o &#xD;&#xA;simp &#x996B;.</p><p class=\"pre-inline\"><b>Decomposition notes 字形分解说明 <a href=\"https://dixin.github.io/Etymology/decomposition-of-chinese-character\" target=\"_blank\" title=\"Help: Decomposition of Chinese character\"></a>:</b><br/></p><p><b>Simplification rule <a target=\"_blank\" ></a>:</b></p><p class=\"pre-inline\"><b>Simplification rule explained <a target=\"_blank\" ></a>:</b><br/></p><p><b>Variant rule :</b></p><p class=\"pre-inline\"><b>Variant rule clarification <a target=\"_blank\" ></a>:</b><br/></p><p><b>Applied rules <a target=\"_blank\" ></a>:</b> R02 &#x9963;&#x98E0;&#x98DF;</p><p><b>New font rule <a target=\"_blank\" ></a>:</b></p><a target=\"_blank\" ><span ></span></a></div></div><div class=\"col-md-9 col-sm-8 etymology-result bg-primary p-1\" id=\"etymologyCharacters\"><h3><span ></span> </h3><p>There is no known oracle characters found. 没.</p><hr/><h3><span ></span> </h3><p>There is no known bronze characters found. 没.</p><hr/><h3><span ></span> </h3><p>There is no known seal characters found. 没.</p><hr/><h3><span ></span> Liushutong characters (2)</h3><ul class=\"list-inline list-unstyled\"><li class=\"text-center\"><img src=\"hanziyan-L20350.png\"/></li><li class=\"text-center\"><img src=\"hanziyan-L20351.png\"/></li></ul></div></div></div>","rendered":"<span class=\"strokeorderkanji verylarge\">饫</span><span class=\"large strokeorderhanzi\">饫</span><span class=\"large\" style=\"font-family:yugothb\">饫</span>\n<hr>\n<div id=\"chinese_opposite\"><span class=\"strokeorderkanji verylarge\">飫</span> <span class=\"large strokeorderhanzi\">飫</span> <span class=\"large\" style=\"font-family:yugothb\">飫</span></div>\n<hr>\n<div class=\"my-pinyin-image-container pinyin-number-4 pinyin-yu\"><span></span><img><img></div>\n<div class=\"my-pinyin-tone\"><a href=\"allsetlearning-yu4.mp3\" class=\"pinyin tone4\">yù</a></div>\n<div class=\"my-pinyin-english\">full (as of eating)</div>\n<div class=\"my-pinyin-ru\">полный (после еды)</div>[anki:play:a:0]<br>\n<div class=\"tl\" id=\"russian\" style=\"color:#ff9e9e\">Trainchinese:</div><span class=\"trainchinese-pinyin\">yù</span>: (<span class=\"trainchinese-type\">графема</span>) <span class=\"trainchinese-transl\">(книжн.) наесться до отвала, насытиться</span>\n<hr>Links: <a href=\"aedict://饫\">aedict</a> | <a href=\"http://jisho.org/kanji/details/饫\">jisho</a> | <a href=\"http://kanji.koohii.com/study/kanji/饫\">koohii</a> | <a href=\"https://hanziyuan.net/#饫\">hanziyuan</a> | <a href=\"https://www.kanshudo.com/kanji/饫\">kanshudo</a> | <a href=\"https://en.m.wiktionary.org/wiki/饫\">wiktionary</a> | <a href=\"https://www.purpleculture.net/dictionary_details/?word=饫\">purpleculture</a> | <a href=\"http://rtega.be/chmn/?c=饫\">rtega</a> | <a href=\"https://www.trainchinese.com/v2/search.php?searchWord=饫&tcLanguage=ru\">trainchinese</a> | <a href=\"https://bkrs.info/slovo.php?ch=饫&tcLanguage=ru\">bkrs</a> | <a href=\"http://humanum.arts.cuhk.edu.hk/Lexis/lexi-mf/search.php?word=饫\">humanum</a> | <a href=\"https://baike.baidu.com/item/饫\">Baido</a> | <a href=\"https://www.yw11.com/zidian/index/search/饫\">yw11</a> | <a href=\"plecoapi://x-callback-url/s?q=饫\">Pleco Search</a> | <a href=\"plecoapi://x-callback-url/s?mode=df&hw=饫&sec=dict&x-source=Anki\">Pleco</a>\n<hr>\n<div id=\"ch_with_same_pronounciation\">\n  <div class=\"pinyin\">yu4</div>\n  <div class=\"same-pronounciation\">\n    <div class=\"row row-hsk-1\"><span class=\"key\">HSK 1</span>: <span class=\"kanji\">语</span>,<span class=\"kanji\">雨</span>,<span class=\"kanji\">語</span></div>\n    <div class=\"row row-hsk-3\"><span class=\"key\">HSK 3</span>: <span class=\"kanji\">育</span>,<span class=\"kanji\">遇</span></div>\n    <div class=\"row row-hsk-4\"><span class=\"key\">HSK 4</span>: <span class=\"kanji\">与</span>,<span class=\"kanji\">预</span>,<span class=\"kanji\">與</span>,<span class=\"kanji\">預</span></div>\n    <div class=\"row row-hsk-5\"><span class=\"key\">HSK 5</span>: <span class=\"kanji\">域</span>,<span class=\"kanji\">豫</span>,<span class=\"kanji\">寓</span></div>\n    <div class=\"row row-hsk-6\"><span class=\"key\">HSK 6</span>: <span class=\"kanji\">獄</span>,<span class=\"kanji\">玉</span>,<span class=\"kanji\">欲</span>,<span class=\"kanji\">愈</span>,<span class=\"kanji\">御</span>,<span class=\"kanji\">狱</span>,<span class=\"kanji\">誉</span>,<span class=\"kanji\">郁</span>,<span class=\"kanji\">裕</span>,<span class=\"kanji\">吁</span>,<span class=\"kanji\">喻</span>,<span class=\"kanji\">浴</span>,<span class=\"kanji\">粥</span>,<span class=\"kanji\">蔚</span>,<span class=\"kanji\">熨</span>,<span class=\"kanji\">鬱</span>,<span class=\"kanji\">禦</span>,<span class=\"kanji\">譽</span></div>\n  </div>\n</div>\n<hr>\n<div id=\"purpleculture_info\">\n  <div>\n    <div>\n      <div><span class=\"tc\">(Trad.: 飫)</span></div>\n      <div><b>Pictophonetic</b>: <span class=\"semantic\"><a class=\"dictips\">夭</a></span> indicates the sound; <span class=\"phonetic\"><a class=\"dictips\">饣</a></span> (eat) conveys the meaning.</div>\n    </div>\n  </div>\n</div>\n<div id=\"purpleculture_tree\">\n  <div class=\"tree\">\n    <ul>\n      <li><span class=\"str_def\">⿰</span> <span class=\"str_desc\">Left to right</span>\n        <ul>\n          <li><span class=\"str_def\"><a class=\"dictips\">饣</a></span> <span class=\"str_py\">[ <a href=\"allsetlearning-shi2.mp3\" class=\"pinyin tone2\">shí</a> ]</span> <span class=\"str_desc\">food; to eat</span></li>\n          <li><span class=\"str_def\"><a class=\"dictips\">夭</a></span> <span class=\"str_py\">[ <a href=\"allsetlearning-yao1.mp3\" class=\"pinyin tone1\">yāo</a> ]</span> <span class=\"str_desc\">young, energetic; to die young</span></li>\n        </ul>\n      </li>\n    </ul>\n  </div>\n</div>\n<hr><span id=\"purpleculture_examples\"><a href=\"https://www.purpleculture.net/dictionary-details?word=%E9%A5%AB%E7%94%98%E9%A4%8D%E8%82%A5\" class=\"sword\">饫甘餍肥</a> [ <a href=\"allsetlearning-yu4.mp3\" class=\"pinyin tone4\">yù</a> <a href=\"allsetlearning-gan1.mp3\" class=\"pinyin tone1\">gān</a> <a href=\"allsetlearning-yan4.mp3\" class=\"pinyin tone4\">yàn</a> <a href=\"allsetlearning-fei2.mp3\" class=\"pinyin tone2\">féi</a> ]: to live off the fat of the land (idiom); to have a luxurious lifestyle</span>\n<hr>\n<div>\n  <div>\n    <div><span class=\"tc\">(Trad.: 飫)</span></div>\n    <div><b>Pictophonetic</b>: <span class=\"semantic\"><a class=\"dictips\">夭</a></span> indicates the sound; <span class=\"phonetic\"><a class=\"dictips\">饣</a></span> (eat) conveys the meaning.</div>\n  </div>\n</div>\n<div>Freq: 5141</div>\n<hr>\n<div><span style=\"color:#f5950f\">Hanzi:</span> 飫<br></div>\n<div>\n  <hr>\n</div>\n<div class=\"two_children__horiz_even\">\n  <div id=\"baidu_chinese\">\n    <div>饫（yù），1.古代家庭私宴的名称。2、饱食。</div>\n  </div>\n  <div id=\"baidu_chinese_en\">\n    <div>饫 (yù), 1. The name of an ancient family banquet. 2. Satiated.</div>\n  </div>\n</div>\n<div id=\"hanziyuan\">\n  <div class=\"etymology-nav\" id=\"&#x996B;\">\n    <div class=\"alert alert-success etymology-alert m-0\" role=\"alert\"></div>\n    <div class=\"row bg-info border-purple border-top mx-0 row-eq-height\" id=\"E07729\">\n      <div class=\"col-md-3 col-sm-4 p-0\">\n        <div class=\"p-1\">\n          <p></p>\n          <p><b>Traditional in your browser 繁体字的浏览器显示:</b><span class=\"text-lg\">&#x98EB;</span></p>\n          <p><b>Traditional in Unicode standard 繁体字的Unicode标准:</b><a href=\"https://www.unicode.org/cgi-bin/GetUnihanData.pl?codepoint=98EB\" target=\"_blank\">U+98EB</a><img src=\"https://www.unicode.org/cgi-bin/refglyph?24-98EB\"></p>\n          <p><b>Older traditional characters 旧繁体字/异体字:</b> Not exist</p>\n          <p><b>Simplified in your browser 简体字的浏览器显示:</b><span class=\"text-lg\">&#x996B;</span></p>\n          <p><b>Simplified in Unicode standard 简体字的Unicode标准:</b><a href=\"https://www.unicode.org/cgi-bin/GetUnihanData.pl?codepoint=996B\" target=\"_blank\">U+996B</a><img src=\"https://www.unicode.org/cgi-bin/refglyph?24-996B\"></p>\n          <p><b>Main pronunciation 主要发音:</b> y&#xF9;</p>\n          <p><b>Other pronunciations 其它发音:</b> Not exists.</p>\n          <p><b>Original meaning 本义:</b> Meaning surfeited, satiated; confer</p>\n          <p><b>English senses 英语理解:</b></p>\n          <p><b>Usage example 用法举例:</b></p>\n          <p><b>Importance by frequency 常用频率:</b></p>\n          <p><b>Shuowen 说文解字:</b></p>\n          <p class=\"pre-inline\"><b>Character decomposition 字形分解 <a href=\"https://dixin.github.io/Etymology/decomposition-of-chinese-character\" target=\"_blank\" title=\"Help: Decomposition of Chinese character\"></a>:</b><br>Compound &#x98EB; &#xD;&#xA;from mouth-eating (&#x9963;)&#x98E0;&#x98DF; sh&#xED; and &#xD;&#xA;phonetic young-person &#x592D; y&#x101;o &#xD;&#xA;simp &#x996B;.</p>\n          <p class=\"pre-inline\"><b>Decomposition notes 字形分解说明 <a href=\"https://dixin.github.io/Etymology/decomposition-of-chinese-character\" target=\"_blank\" title=\"Help: Decomposition of Chinese character\"></a>:</b><br></p>\n          <p><b>Simplification rule <a target=\"_blank\"></a>:</b></p>\n          <p class=\"pre-inline\"><b>Simplification rule explained <a target=\"_blank\"></a>:</b><br></p>\n          <p><b>Variant rule :</b></p>\n          <p class=\"pre-inline\"><b>Variant rule clarification <a target=\"_blank\"></a>:</b><br></p>\n          <p><b>Applied rules <a target=\"_blank\"></a>:</b> R02 &#x9963;&#x98E0;&#x98DF;</p>\n          <p><b>New font rule <a target=\"_blank\"></a>:</b></p><a target=\"_blank\"><span></span></a>\n        </div>\n      </div>\n      <div class=\"p-1 bg-primary col-md-9 col-sm-8 etymology-result\" id=\"etymologyCharacters\">\n        <h3><span></span></h3>\n        <p>There is no known oracle characters found. 没.</p>\n        <hr>\n        <h3><span></span></h3>\n        <p>There is no known bronze characters found. 没.</p>\n        <hr>\n        <h3><span></span></h3>\n        <p>There is no known seal characters found. 没.</p>\n        <hr>\n        <h3><span></span> Liushutong characters (2)</h3>\n        <ul class=\"list-inline list-unstyled\">\n          <li class=\"text-center\"><img src=\"hanziyan-L20350.png\"></li>\n          <li class=\"text-center\"><img src=\"hanziyan-L20351.png\"></li>\n        </ul>\n      </div>\n    </div>\n  </div>\n</div>\n<div class=\"two_children__horiz_even\">\n  <div id=\"yw11\">\n    <h4><span>饫</span>字的基本解释</h4>\n    <div>\n      <p>饫<br>（飫）<br>yù<br>古代家庭私宴的名称。<br>饱食。<br><br></p>\n    </div>\n    <div><span>饫</span>字的汉语字典释义</div>\n    <div>\n      <p>[①]［yù］<br>［《廣韻》依倨切，去御，影。］<br>亦作“秗1”。“淤2”的被通假字。“饫1”的繁体字。<br>(1)古代家族的私宴名。<br>(2)古代立着举行、昭明大节的宴礼。<br>(3)宴食；宴饮。<br>(4)饱食。<br>(5)引申为尽情地舔。<br>(6)足；饱。<br>(7)指饫闻。<br>(8)肥美。<br>(9)赐予（食物）。</p>\n    </div>\n    <div><span>饫</span>字的康熙字典解释</div>\n    <div>\n      <p>【戌集下】【食字部】　飫； 康熙笔画：13； 页码：<a href=\"https://images.yw11.com/kangxi/1427.gif\" target=\"_blank\"><span>页1427第31</span></a><br>〔古文〕秗【廣韻】依倨切【集韻】【韻會】【正韻】依據切，?音淤。【玉篇】食多也。【廣韻】飽也，饜也。　又【說文】燕食也。本作?。【詩·小雅】儐爾籩豆，飮酒之飫。【毛傳】儐，?。飫，私也。不脫屨升堂謂之飫。【鄭箋】私者，圖非常之事。若議大疑於堂，則有飫禮焉。【朱傳】飫，饜也。　又【周語】王公立飫，則有房烝，王公諸侯之有飫也，將以講事成章，建大德，昭大物也，故立成禮，烝而已。又武王克殷，作飫歌。【韋昭曰】立謂立行禮不坐也。立曰飫，坐曰晏。歌辭，互見支字註。　又【廣韻】賜也。【左傳·襄二十六年】將賞爲之加膳，加膳則飫賜。　又【尚書序】逸書有?飫篇名。【傳】?，勞。飫，賜也。　【集韻】或作饇?。</p>\n      <hr>考證：〔【周語】王公立飫，則有房丞〕　謹照原文房丞改房烝。\n    </div>\n    <div><span>饫</span>字的源字形</div>\n    <div>\n      <h3>字源演变：</h3><span><span><img src=\"yw11-zixing-996B.gif\">小篆</span><span><img src=\"yw11-zixing-996B.gif\">楷体</span></span>\n      <h3>字形对比：</h3><span><span><img src=\"yw11-zixing-996B.gif\">中国大陆宋体</span><span><img src=\"yw11-zixing-996B.gif\">台湾细明体</span><span><img src=\"yw11-zixing-996B.gif\">韩国明朝体</span><span><img src=\"yw11-zixing-996B.gif\">旧字形</span></span>\n    </div>\n    <div><span>饫</span>字的起名意思</div>\n    <div>\n      <p>暂无。</p>\n    </div>\n  </div>\n  <div id=\"yw11_en_transl\">饫<br>Basic explanation of words<br>饫<br>(饫)<br>yù<br>The name of an ancient family banquet.<br>Satiety.<br>饫<br>Chinese dictionary definition of words<br>[①]［yù］<br>[\"Guang Yun\" cuts according to cluelessness, goes to imperial, shadows. ]<br>Also known as \"秗1\". The word \"silt 2\" was passed falsely. Traditional characters for \"饫1\".<br>(1) The name of the private feast of the ancient family.<br>(2) In ancient times, there was a banquet for Zhaoming Festival.<br>(3) Feast; feast.<br>(4) Satiated.<br>(5) The extension is licking heartily.<br>(6) Full; full.<br>(7) Refers to the smell.<br>(8) Plump.<br>(9) Give (food).<br>饫<br>Kangxi dictionary interpretation of words<br>【戌集下】【Shizi Department】　饫; Kangxi strokes: 13; Page number: page 1427 to 31<br>[Ancient text] Sha [Guang Yun] Cut according to the idiot [Ji Yun] [Yun Hui] [Zheng Yun] According to the cut,? Sound silt. [Jade articles] There is a lot of food. [Guangyun] Full and satisfying.　[Said Wen] Yan Shiya. This work?. 【Poetry·Xiaoya】Liaoerqing bean, the delicacy of wine. [Mao Biography] Grandma,?.饫, private too. Do not take off the 屦屦升堂 called the 饫. [Zheng Jian] Private person, the picture is extraordinary. If there is a big doubt in the hall, there is a feast. [Zhu Chuan] 饫, 餍也.　 [Zhou Yu] Wang Gongli, then there is Fang Zheng, and the princes and princes have Fu also, they will be chapters by talking about things, building great virtues, and showing great things, so Li Cheng Li is just a tribute. And Wu Wang Ke Yin, composing a song. [Wei Zhaoyue] It is said that it is not necessary to sit down and salute. Li said 饫, sitting said Yan. Song Ci, see each other's notes.　[Guangyun] Thanks again. [Zuo Zhuan·Xiang Twenty-sixth Year] Give the reward to the food, and the food to the reward.　[Shang Shu Preface] Yi Shu has a title? [Biography]?, Lao.饫, give it too.　【Ji Yun】or make a sorrow?. Textual research: [[Zhou Yu] Wang Gongli, then Fang Cheng] 　 I would like to change the original Fang Cheng to Fang Zuo.<br>饫<br>Source glyph<br>Character evolution: Xiaozhuan<br>Italics<br>Font comparison: Song Ti, Mainland China<br>Taiwan Minutes<br>Korean Ming Dynasty<br>Old glyph<br>饫<br>Name meaning<br>Nothing.</div>\n</div>\n<div></div>\n<hr>\n<div id=\"bkrs_pinyin\">yù</div>\n<div id=\"bkrs_transl\">\n  <div><strong>I</strong><i> гл.</i></div>\n  <div>наедаться до отвала; насыщаться; досыта, вдоволь, до предела</div>\n  <div><span class=\"example-item\">饱饫 насыщаться до отвала</span></div>\n  <div><span class=\"example-item\">饫听 наслушаться, набраться впечатлений от музыки</span></div>\n  <div><strong>II</strong><i> сущ.</i></div>\n  <div>пир (<i>домашний</i>), пирушка</div>\n  <div><span class=\"example-item\">饫歌 застольная песня</span></div>\n</div>\n<p><a href=\"https://www.mdbg.net/chinese/dictionary?page=worddict&wdrst=0&wdqtm=0&wdqcham=1&wdqt=\">MDBG</a> | <a href=\"https://bkrs.info/slovo.php?ch=饫\">BKRS</a> | <a href=\"https://dictionary.writtenchinese.com/#sk=饫&svt=pinyin\">WriCh</a> | <a href=\"http://www.qianyix.com/words/index.php?q=饫\">Qianyix</a> | <a href=\"https://www.yellowbridge.com/chinese/sentsearch.php?word=饫\">YBridge</a> | <a href=\"http://cca.xingtanlu.cn/?action=page&pid=8&do=search&name=饫\">Collocs</a> | <a href=\"https://characterpop.com/explode/饫\">ChPop</a> | <a href=\"https://visualchinesesearch.com/?query=饫\">SimCh</a> | <a href=\"http://www.hanzicraft.com/character/饫\">Stats</a> | <a href=\"https://www.google.com.au/search?q=饫&tbm=isch\">Google Images</a> | <a href=\"https://namakajiri.net/kanjigen/#饫\">Char lookup site</a></p>","glyphs":[{"glyph":"饣","pinyins":["shi2"]},{"glyph":"夭","pinyins":["yao1"]}]}